LICENSE
README.md
setup.cfg
setup.py
evernode/__init__.py
evernode/evernode.py
evernode.egg-info/PKG-INFO
evernode.egg-info/SOURCES.txt
evernode.egg-info/dependency_links.txt
evernode.egg-info/entry_points.txt
evernode.egg-info/requires.txt
evernode.egg-info/top_level.txt
evernode/bin/__init__.py
evernode/bin/create.py
evernode/bin/module.py
evernode/classes/__init__.py
evernode/classes/app.py
evernode/classes/base_response.py
evernode/classes/cron.py
evernode/classes/email.py
evernode/classes/fail2ban.py
evernode/classes/form_data.py
evernode/classes/json.py
evernode/classes/json_response.py
evernode/classes/jwt.py
evernode/classes/load_language_files.py
evernode/classes/load_modules.py
evernode/classes/middleware.py
evernode/classes/paginate.py
evernode/classes/render.py
evernode/classes/security.py
evernode/classes/session.py
evernode/classes/singleton.py
evernode/classes/translator.py
evernode/classes/user_auth.py
evernode/decorators/__init__.py
evernode/decorators/middleware.py
evernode/functions/__init__.py
evernode/functions/utils.py
evernode/middleware/__init__.py
evernode/middleware/jwt_middleware.py
evernode/middleware/route_before_middleware.py
evernode/middleware/session_middleware.py
evernode/models/__init__.py
evernode/models/base_model.py
evernode/models/base_user_model.py
evernode/models/database_model.py
evernode/models/fail2ban_model.py
evernode/models/json_model.py
evernode/models/password_reset_model.py
evernode/models/response_model.py
evernode/models/session_model.py
evernode/scripts/__init__.py
evernode/scripts/sendemail.py