Metadata-Version: 1.1
Name: evernode
Version: 1.6.1
Summary: EverNode is built by expanding upon flask by adding great features and easy-to-use modular design.
Home-page: https://github.com/atomhash/evernode
Author: AtomHash
Author-email: UNKNOWN
License: UNKNOWN
Download-URL: https://github.com/atomhash/evernode/archive/1.6.1.tar.gz
Keywords: server,flask-based,restful,modular,evernode
Platform: UNKNOWN
